postnl/__init__.py
postnl/api_helper.py
postnl/configuration.py
postnl/postnl_client.py
postnl/controllers/__init__.py
postnl/controllers/barcode_controller.py
postnl/controllers/base_controller.py
postnl/controllers/checkout_controller.py
postnl/controllers/confirming_controller.py
postnl/controllers/deliverydate_controller.py
postnl/controllers/labelling_controller.py
postnl/controllers/locations_controller.py
postnl/controllers/postalcode_check_controller.py
postnl/controllers/shipment_controller.py
postnl/controllers/timeframes_controller.py
postnl/controllers/track_trace_controller.py
postnl/exceptions/__init__.py
postnl/exceptions/api_exception.py
postnl/exceptions/barcode_method_not_allowed_exception.py
postnl/exceptions/barcode_response_error_exception.py
postnl/exceptions/barcode_response_invalid_exception.py
postnl/exceptions/barcode_too_many_request_exception.py
postnl/exceptions/checkout_response_invalid_exception.py
postnl/exceptions/confirming_response_error_1_exception.py
postnl/exceptions/deliverydate_response_invalid_exception.py
postnl/exceptions/labelling_response_invalid_exception.py
postnl/exceptions/locations_response_invalid_exception.py
postnl/exceptions/timeframe_response_invalid_exception.py
postnl/http/__init__.py
postnl/http/api_response.py
postnl/http/http_call_back.py
postnl/http/http_method_enum.py
postnl/http/http_request.py
postnl/http/http_response.py
postnl/http/auth/__init__.py
postnl/http/auth/custom_header_authentication.py
postnl/models/__init__.py
postnl/models/address.py
postnl/models/address_1.py
postnl/models/address_11.py
postnl/models/address_2.py
postnl/models/address_3.py
postnl/models/address_4.py
postnl/models/address_type_enum.py
postnl/models/amount.py
postnl/models/amount_1.py
postnl/models/barcode_response.py
postnl/models/checkout_request.py
postnl/models/checkout_response.py
postnl/models/code_enum.py
postnl/models/complete_status.py
postnl/models/confirming_request.py
postnl/models/confirming_response.py
postnl_sdk-1.0.2.dist-info/LICENSE
postnl_sdk-1.0.2.dist-info/METADATA
postnl_sdk-1.0.2.dist-info/WHEEL
postnl_sdk-1.0.2.dist-info/top_level.txt
postnl_sdk-1.0.2.dist-info/RECORD
