Metadata-Version: 2.1
Name: postnl-sdk
Version: 1.0.2
Summary: Collection of PostNL API's for ecommerce processes.
Author-email: PostNL <apimatic@postnl.nl>
Project-URL: Documentation, https://developer.postnl.nl/
Keywords: PostNL,SDK,API,ecommerce
Requires-Python: >=3.7
License-File: LICENSE
Requires-Dist: apimatic-core ~=0.2.0
Requires-Dist: apimatic-core-interfaces ~=0.1.0
Requires-Dist: apimatic-requests-client-adapter ~=0.1.0
Requires-Dist: enum34 >=1.1.10,~=1.1
Provides-Extra: testutils
Requires-Dist: pytest >=7.2.2 ; extra == 'testutils'
